apillama/__init__.py
apillama/apillama.py
apillama-0.1.5.dist-info/LICENSE
apillama-0.1.5.dist-info/METADATA
apillama-0.1.5.dist-info/WHEEL
apillama-0.1.5.dist-info/RECORD
