Metadata-Version: 2.1
Name: apillama
Version: 0.1.5
Summary: 
License: MIT
Author: Eduardo Reis
Author-email: edu.pontes@gmail.com
Requires-Python: >=3.9,<4.0
Classifier: License :: OSI Approved :: MIT License
Classifier: Programming Language :: Python :: 3
Classifier: Programming Language :: Python :: 3.9
Classifier: Programming Language :: Python :: 3.10
Classifier: Programming Language :: Python :: 3.11
Requires-Dist: aiohttp (>=3.8.5,<4.0.0)
Requires-Dist: nest-asyncio (>=1.5.6,<2.0.0)
Requires-Dist: requests (>=2.31.0,<3.0.0)
